[
  {
    "id": 1,
    "name": "Sugeng No Pants",
    "address": "Cileungsi",
    "postCode": "16820",
    "income": 39000,
    "order": [
      {
        "id": 1,
        "img": "/static/media/img2.7403eb95.svg",
        "product_name": "Ice Coffee Green Tea",
        "subtotal": 36000,
        "tgl": "22 August 2021",
        "topping": [
          {
            "id": 2,
            "name": "Mango",
            "price": 3000,
            "imgUrl": "/img/topping/2.png"
          }
        ]
      }
    ],
    "status": "Waiting Approve"
  }
]
